{"types":"","keywords":["engineio","socketio","engineio-parser","OpenHarmony","HarmonyOS"],"author":"yangyongzhen","description":"This is the JavaScript parser for the engine.io protocol encoding, 本软件是移植开源软件engine.io-parser源码在OpenHarmony上进行功能适配。","main":"index.ts","repository":"https://gitee.com/yyz116/engine.io-parser","type":"module","version":"1.0.1","dependencies":{},"tags":["Tools","Network"],"license":"MIT","homepage":"https://gitee.com/yyz116","devDependencies":{},"name":"@yyz116/engine.io-parser","metadata":{"sourceRoots":["./src/main"]},"compatibleSdkVersion":12,"compatibleSdkType":"HarmonyOS","obfuscated":false}
